ibats_trader/__init__.py
ibats_trader/config.py
ibats_trader/event.py
ibats_trader/md.py
ibats_trader/strategy.py
ibats_trader/trade.py
ibats_trader/backend/__init__.py
ibats_trader/backend/orm.py
IBATSTrader-0.1.3.dist-info/LICENSE
IBATSTrader-0.1.3.dist-info/METADATA
IBATSTrader-0.1.3.dist-info/WHEEL
IBATSTrader-0.1.3.dist-info/top_level.txt
IBATSTrader-0.1.3.dist-info/RECORD
