Metadata-Version: 2.1
Name: IBATSTrader
Version: 0.1.3
Summary: IBATS（Integration Backtest Analysis Trade System）的Trader端公共模块，所有 Trader均集成这个模块，并使用其提供的一些公共工具
Home-page: https://github.com/mmmaaaggg/IBATS_Trader
Author: MG
Author-email: mmmaaaggg@163.com
License: UNKNOWN
Platform: UNKNOWN
Classifier: Programming Language :: Python :: 3 :: Only
Classifier: Programming Language :: Python :: 3.6
Classifier: Programming Language :: Python :: 3.7
Classifier: Operating System :: Microsoft :: Windows
Classifier: Operating System :: Unix
Classifier: Operating System :: POSIX
Classifier: License :: OSI Approved :: MIT License
Classifier: Development Status :: 5 - Production/Stable
Classifier: Environment :: No Input/Output (Daemon)
Classifier: Intended Audience :: Developers
Classifier: Natural Language :: Chinese (Simplified)
Classifier: Topic :: Software Development
Requires-Python: >=3.6
Requires-Dist: IBATSCommon
